{
    "query": "{\"c\":1,\"type\":\"adm_reg\",\"uid\":\"72\",\"rows\":{\"reg_mean_ndvi_7dc_modis_int_ozim\":[2021]}}",
    "data": {
        "1": {
            "width": 2,
            "y_min": 0,
            "marks": 0,
            "yAxisTitle": "Вегетационный индекс NDVI",
            "norm": 0,
            "name_class": "",
            "color": "#ff9933",
            "xy": [
                [
                    "56",
                    0.012
                ],
                [
                    "63",
                    0.061
                ],
                [
                    "70",
                    0.116
                ],
                [
                    "77",
                    0.171
                ],
                [
                    "84",
                    0.225
                ],
                [
                    "91",
                    0.304
                ],
                [
                    "98",
                    0.311
                ],
                [
                    "105",
                    0.343
                ],
                [
                    "112",
                    0.401
                ],
                [
                    "119",
                    0.465
                ],
                [
                    "126",
                    0.532
                ],
                [
                    "133",
                    0.598
                ],
                [
                    "140",
                    0.678
                ],
                [
                    "147",
                    0.756
                ],
                [
                    "154",
                    0.811
                ],
                [
                    "161",
                    0.844
                ],
                [
                    "168",
                    0.859
                ],
                [
                    "175",
                    0.843
                ],
                [
                    "182",
                    0.792
                ],
                [
                    "189",
                    0.716
                ],
                [
                    "196",
                    0.607
                ],
                [
                    "203",
                    0.513
                ],
                [
                    "210",
                    0.46
                ],
                [
                    "217",
                    0.425
                ],
                [
                    "224",
                    0.412
                ],
                [
                    "231",
                    0.411
                ],
                [
                    "238",
                    0.421
                ],
                [
                    "245",
                    0.432
                ],
                [
                    "252",
                    0.438
                ],
                [
                    "259",
                    0.446
                ],
                [
                    "266",
                    0.447
                ],
                [
                    "273",
                    0.444
                ],
                [
                    "280",
                    0.495
                ],
                [
                    "287",
                    0.522
                ],
                [
                    "294",
                    0.543
                ],
                [
                    "301",
                    0.567
                ],
                [
                    "308",
                    0.592
                ],
                [
                    "315",
                    0.612
                ],
                [
                    "322",
                    0.608
                ],
                [
                    "329",
                    0.563
                ]
            ],
            "id": 1,
            "labels": {
                "63": "2021-03-07",
                "70": "2021-03-14",
                "322": "2021-11-21",
                "315": "2021-11-14",
                "119": "2021-05-02",
                "329": "2021-11-28",
                "84": "2021-03-28",
                "147": "2021-05-30",
                "252": "2021-09-12",
                "161": "2021-06-13",
                "182": "2021-07-04",
                "280": "2021-10-10",
                "259": "2021-09-19",
                "273": "2021-10-03",
                "168": "2021-06-20",
                "308": "2021-11-07",
                "231": "2021-08-22",
                "112": "2021-04-25",
                "224": "2021-08-15",
                "175": "2021-06-27",
                "140": "2021-05-23",
                "189": "2021-07-11",
                "217": "2021-08-08",
                "245": "2021-09-05",
                "287": "2021-10-17",
                "91": "2021-04-04",
                "266": "2021-09-26",
                "294": "2021-10-24",
                "77": "2021-03-21",
                "154": "2021-06-06",
                "105": "2021-04-18",
                "133": "2021-05-16",
                "301": "2021-10-31",
                "126": "2021-05-09",
                "238": "2021-08-29",
                "203": "2021-07-25",
                "210": "2021-08-01",
                "98": "2021-04-11",
                "56": "2021-02-28",
                "196": "2021-07-18"
            },
            "point_id": null,
            "count": null,
            "style": "#2020202",
            "y_max": 1,
            "y_dy": null,
            "y_axis_type": "ndvi",
            "scale": 7,
            "product": "reg_mean_ndvi_7dc_modis_int_ozim",
            "ndvi": 0,
            "title": "Тульская область <br>NDVI, MODIS (интерполяция) средний по региону (земли, занятые озимыми), 2021 год",
            "year": "2021"
        }
    },
    "nocache": "34576",
    "xAxisTitle": "Номер недели в году",
    "x_axis_type": "time"
}