{
    "query": "{\"c\":1,\"type\":\"adm_dis\",\"uid\":\"271\",\"rows\":{\"mean_ndvi_7dc_modis_int_ozim\":[2015]}}",
    "data": {
        "1": {
            "width": 2,
            "y_min": 0,
            "marks": 0,
            "yAxisTitle": "Вегетационный индекс NDVI",
            "norm": 0,
            "name_class": "",
            "color": "#ff66ff",
            "xy": [
                [
                    "84",
                    0.217
                ],
                [
                    "91",
                    0.224
                ],
                [
                    "98",
                    0.227
                ],
                [
                    "105",
                    0.281
                ],
                [
                    "112",
                    0.336
                ],
                [
                    "119",
                    0.409
                ],
                [
                    "126",
                    0.488
                ],
                [
                    "133",
                    0.585
                ],
                [
                    "140",
                    0.672
                ],
                [
                    "147",
                    0.751
                ],
                [
                    "154",
                    0.798
                ],
                [
                    "161",
                    0.822
                ],
                [
                    "168",
                    0.783
                ],
                [
                    "175",
                    0.684
                ],
                [
                    "182",
                    0.566
                ],
                [
                    "189",
                    0.483
                ],
                [
                    "196",
                    0.444
                ],
                [
                    "203",
                    0.43
                ],
                [
                    "210",
                    0.425
                ],
                [
                    "217",
                    0.41
                ],
                [
                    "224",
                    0.384
                ],
                [
                    "231",
                    0.366
                ],
                [
                    "238",
                    0.353
                ],
                [
                    "245",
                    0.334
                ],
                [
                    "252",
                    0.315
                ],
                [
                    "259",
                    0.306
                ],
                [
                    "266",
                    0.297
                ],
                [
                    "273",
                    0.287
                ],
                [
                    "280",
                    0.274
                ],
                [
                    "287",
                    0.511
                ],
                [
                    "294",
                    0.53
                ],
                [
                    "301",
                    0.548
                ],
                [
                    "308",
                    0.574
                ],
                [
                    "315",
                    0.594
                ],
                [
                    "322",
                    0.608
                ],
                [
                    "329",
                    0.621
                ],
                [
                    "336",
                    0.633
                ],
                [
                    "343",
                    0.643
                ],
                [
                    "350",
                    0.652
                ],
                [
                    "357",
                    0.672
                ],
                [
                    "364",
                    0.695
                ],
                [
                    "371",
                    0.719
                ]
            ],
            "id": 1,
            "labels": {
                "371": "2016-01-03",
                "322": "2015-11-15",
                "336": "2015-11-29",
                "315": "2015-11-08",
                "119": "2015-04-26",
                "329": "2015-11-22",
                "84": "2015-03-22",
                "147": "2015-05-24",
                "252": "2015-09-06",
                "161": "2015-06-07",
                "182": "2015-06-28",
                "280": "2015-10-04",
                "259": "2015-09-13",
                "273": "2015-09-27",
                "168": "2015-06-14",
                "308": "2015-11-01",
                "231": "2015-08-16",
                "112": "2015-04-19",
                "224": "2015-08-09",
                "175": "2015-06-21",
                "140": "2015-05-17",
                "343": "2015-12-06",
                "189": "2015-07-05",
                "217": "2015-08-02",
                "245": "2015-08-30",
                "91": "2015-03-29",
                "266": "2015-09-20",
                "287": "2015-10-11",
                "294": "2015-10-18",
                "154": "2015-05-31",
                "364": "2015-12-27",
                "133": "2015-05-10",
                "105": "2015-04-12",
                "126": "2015-05-03",
                "301": "2015-10-25",
                "350": "2015-12-13",
                "238": "2015-08-23",
                "203": "2015-07-19",
                "210": "2015-07-26",
                "98": "2015-04-05",
                "357": "2015-12-20",
                "196": "2015-07-12"
            },
            "point_id": null,
            "count": null,
            "style": "#2020202",
            "y_max": 1,
            "y_dy": null,
            "y_axis_type": "ndvi",
            "scale": 7,
            "product": "mean_ndvi_7dc_modis_int_ozim",
            "ndvi": 0,
            "title": "Воронежская область - Воробьевский район <br>NDVI, MODIS (интерполяция) средний по району (земли, занятые озимыми), 2015 год",
            "year": "2015"
        }
    },
    "nocache": null,
    "xAxisTitle": "Номер недели в году",
    "x_axis_type": "time"
}